{"aliases": ["THE VOC＠LOiD M＠STER 49", "ボーマス49", "VOM@S49"], "dates": "2022.11.12", "circles": [{"aliases": ["藍瀬 まなみ&いがきち&柚璃遥"], "pen_names": ["藍瀬 まなみ、いがきち、柚璃遥"], "position": "A13.14", "links": ["https://596ab8.myportfolio.com/", "http://x.com/iga_kitty"], "comments": "Kana prefix: アイ"}, {"aliases": ["哀乃"], "pen_names": ["哀乃"], "position": "C15", "links": ["https://www.youtube.com/c/%E5%93%80%E4%B9%83", "http://x.com/ainodesuyo2"], "comments": "Kana prefix: アイ"}, {"aliases": ["あいのて"], "pen_names": ["appy"], "position": "E22", "links": ["https://mahorobalaboratory.wixsite.com/appy", "http://x.com/appy_7", "http://www.pixiv.net/member.php?id=5378863"], "comments": "Kana prefix: アイ"}, {"aliases": ["青い向日葵"], "pen_names": ["白雪とわ"], "position": "B47", "links": ["https://kirakirakisora.tumblr.com/", "http://x.com/ShirayukiTowa", "http://www.pixiv.net/member.php?id=2286680"], "comments": "Kana prefix: アオ"}, {"aliases": ["蒼巳生姜本舗"], "pen_names": ["蒼巳生姜"], "position": "F61", "links": ["https://syougatougarasi.wixsite.com/syougawork", "http://x.com/syo_u_ron", "http://www.pixiv.net/member.php?id=291264"], "comments": "Kana prefix: アオ"}, {"aliases": ["亜歌"], "position": "D35.36", "links": ["https://lit.link/akappella", "http://x.com/aka_acappella"], "comments": "Kana prefix: アカ"}, {"aliases": ["akatsukikyo Music Channel"], "pen_names": ["akatsukikyo"], "position": "E36", "links": ["http://akatsukikyo.xsrv.jp/", "http://x.com/akatsukikyo0707"], "comments": "Kana prefix: アカ"}, {"aliases": ["アクラスルウム"], "pen_names": ["しとらの、暖炉P、わらべ、ぱいなぽる、灰葉狼"], "position": "W13.14", "links": ["http://x.com/shitorano", "http://www.nicovideo.jp/user/121169424"], "comments": "Kana prefix: アク"}, {"aliases": ["あ子"], "pen_names": ["あ子"], "position": "B49", "links": ["https://akokkokokko.wixsite.com/akoyade", "http://x.com/ako_okko", "http://www.pixiv.net/member.php?id=32100418"], "comments": "Kana prefix: アコ"}, {"aliases": ["Advanced Music products"], "pen_names": ["AM-p"], "position": "E35", "links": ["https://amp4561701.wixsite.com/am-p", "http://x.com/Ap36288136", "http://www.pixiv.net/member.php?id=35092810"], "comments": "Kana prefix: アド"}, {"aliases": ["ATOLS"], "pen_names": ["ATOLS"], "position": "W11.12", "links": ["http://atols.net/", "http://x.com/ATOLSX", "http://www.nicovideo.jp/user/1695193"], "comments": "Kana prefix: アト"}, {"aliases": ["アノオト"], "pen_names": ["反骨P"], "position": "D66", "links": ["https://note.com/hankotsu_soul", "http://x.com/hankotsu_p", "http://www.nicovideo.jp/user/118839565"], "comments": "Kana prefix: アノ"}, {"aliases": ["雨上がりレコーズ"], "pen_names": ["のーねーむ"], "position": "E18", "links": ["https://www.nicovideo.jp/series/76550", "http://x.com/no_name_poem"], "comments": "Kana prefix: アメ"}, {"aliases": ["鮎川乱舞"], "pen_names": ["鮎川 ぱて"], "position": "E72", "links": ["http://x.com/ayupate", "http://www.nicovideo.jp/user/1057645"], "comments": "Kana prefix: アユ"}, {"aliases": ["Unlimited Color"], "pen_names": ["OTIKA(からし蓮根P)、NAMBO"], "position": "C46", "links": ["https://unlimited-color.com", "http://x.com/otikaplus2", "http://www.pixiv.net/member.php?id=20762948"], "comments": "Kana prefix: アン"}, {"aliases": ["家の裏でマンボウが死んでるP"], "pen_names": ["家の裏でマンボウが死んでるP"], "position": "D39.40", "links": ["https://manbo-p.com", "http://x.com/takahashi_manbo", "http://www.nicovideo.jp/user/372592"], "comments": "Kana prefix: イエ"}, {"aliases": ["遺失物取り扱い兎"], "pen_names": ["Yono"], "position": "D59", "links": ["https://linktr.ee/yonori", "http://x.com/yono_p", "http://www.nicovideo.jp/user/194994"], "comments": "Kana prefix: イシ"}, {"aliases": ["いずみ屋さん"], "pen_names": ["灰純アエラ"], "position": "F24", "links": ["http://x.com/ha_izumi_a", "http://www.pixiv.net/member.php?id=878792"], "comments": "Kana prefix: イズ"}, {"aliases": ["一年中夏休み"], "pen_names": ["ナナツナツ"], "position": "C24", "links": ["https://n72tyt.wixsite.com/77272", "http://x.com/72tyt", "http://www.nicovideo.jp/user/34843985"], "comments": "Kana prefix: イチ"}, {"aliases": ["イチミリタマゴ"], "pen_names": ["ミリ子"], "position": "E05", "links": ["https://mirik0v0tosige.wixsite.com/miriko", "http://x.com/miriaru0913", "http://www.nicovideo.jp/user/35267836"], "comments": "Kana prefix: イチ"}, {"aliases": ["イツカのヨルに"], "pen_names": ["或(aru)、幽(iu)"], "position": "C39", "links": ["http://x.com/itk_yrn"], "comments": "Kana prefix: イツ"}, {"aliases": ["いもかまきり"], "pen_names": ["さくま、富郎"], "position": "E45.46", "links": ["https://imokamakiri.booth.pm/", "http://x.com/ykrm01328", "http://www.pixiv.net/member.php?id=3320476"], "comments": "Kana prefix: イモ"}, {"aliases": ["VioletCube"], "pen_names": ["after"], "position": "F45", "links": ["http://x.com/after0217", "http://www.pixiv.net/member.php?id=6725638"], "comments": "Kana prefix: ヴァ"}, {"aliases": ["上野オフ会"], "pen_names": ["めりっさ"], "position": "C18", "links": ["https://www.nicovideo.jp/my/mylist/25833700", "http://x.com/Melissa_1207", "http://www.nicovideo.jp/user/1213205"], "comments": "Kana prefix: ウエ"}, {"aliases": ["うしお屋"], "pen_names": ["うしお"], "position": "D46", "links": ["https://ushioisu.fanbox.cc/", "http://x.com/szkioisu", "http://www.nicovideo.jp/user/39805725"], "comments": "Kana prefix: ウシ"}, {"aliases": ["薄塩指数"], "pen_names": ["薄塩指数"], "position": "E17", "links": ["https://www.youtube.com/channel/UCQlj7cVNN9_gg6XUKj-coJg", "http://x.com/usushioshisuu"], "comments": "Kana prefix: ウス"}, {"aliases": ["ウニの水族館"], "pen_names": ["rukaku"], "position": "W03.04", "links": ["http://x.com/mikuphile"], "comments": "Kana prefix: ウニ"}, {"aliases": ["えいち"], "pen_names": ["えいち"], "position": "D21", "links": ["https://www.nicovideo.jp/mylist/35365503", "http://x.com/donkakusense", "http://www.nicovideo.jp/user/27253704"], "comments": "Kana prefix: エイ"}, {"aliases": ["EO"], "pen_names": ["EO"], "position": "D23", "links": ["https://eoaui7740.wixsite.com/official", "http://x.com/eo_aui7740", "http://www.pixiv.net/member.php?id=61198437"], "comments": "Kana prefix: エオ"}, {"aliases": ["S-Canvas"], "pen_names": ["月灯ゆら、(飲み会芸人P)"], "position": "W19.20", "links": ["http://x.com/yr_nmkiP", "http://www.nicovideo.jp/user/8325877"], "comments": "Kana prefix: エス"}, {"aliases": ["絵空事"], "pen_names": ["ぜんじまる"], "position": "F63", "links": ["http://x.com/zenjimaru39", "http://www.pixiv.net/member.php?id=817646"], "comments": "Kana prefix: エソ"}, {"aliases": ["Eddie K.C."], "pen_names": ["エディ・K・C"], "position": "C16", "links": ["http://x.com/shibarip1"], "comments": "Kana prefix: エデ"}, {"aliases": ["エドガワ"], "pen_names": ["江戸川リバ子"], "position": "C55", "links": ["http://edoriver.starfree.jp/", "http://x.com/edogawa_river"], "comments": "Kana prefix: エド"}, {"aliases": ["EHAMIC"], "pen_names": ["EHAMIC"], "position": "B55", "links": ["http://EHAMIC.com", "http://x.com/EHAMIC", "http://www.nicovideo.jp/user/13310478"], "comments": "Kana prefix: エハ"}, {"aliases": ["L3Project"], "pen_names": ["れれれP"], "position": "D17", "links": ["https://l3project.com/", "http://x.com/lelelep", "http://www.nicovideo.jp/user/112663"], "comments": "Kana prefix: エル"}, {"aliases": ["エレアコ弾きの羽咲りお"], "pen_names": ["羽咲りお"], "position": "E30", "links": ["https://www.nicovideo.jp/my/mylist/73743752", "http://x.com/Rio_Aporoguist", "http://www.nicovideo.jp/user/120572712"], "comments": "Kana prefix: エレ"}, {"aliases": ["endroll fanclub"], "pen_names": ["dyism"], "position": "E32", "links": ["http://x.com/yismsand27"], "comments": "Kana prefix: エン"}, {"aliases": ["おうたっぴずむ"], "pen_names": ["nowism(おうたP)"], "position": "E06", "links": ["http://www.nicovideo.jp/mylist/16649288", "http://x.com/nowism_outaP", "http://www.nicovideo.jp/user/15106796"], "comments": "Kana prefix: オウ"}, {"aliases": ["大江戸宅急便"], "pen_names": ["島村秀行/鼻炎P"], "position": "F23", "links": ["https://www.ooedo.jp/", "http://x.com/shimamurasan", "http://www.pixiv.net/member.php?id=1226572"], "comments": "Kana prefix: オオ"}, {"aliases": ["おつよんズ"], "pen_names": ["乙れん、hayayon"], "position": "F58", "links": ["http://x.com/otsurenn", "http://www.pixiv.net/member.php?id=7300736"], "comments": "Kana prefix: オツ"}, {"aliases": ["音戯噺屋"], "pen_names": ["卑屈P"], "position": "B54", "links": ["http://jirai8.web.fc2.com/gateway.html", "http://x.com/kou46", "http://www.nicovideo.jp/user/234179"], "comments": "Kana prefix: オト"}, {"aliases": ["鬼っ子ハンターついなちゃんプロジェクト"], "pen_names": ["大辺璃 紗季"], "position": "E14", "links": ["https://ついなちゃん.com", "http://x.com/Tuina_chan_PJ", "http://www.pixiv.net/member.php?id=2723539"], "comments": "Kana prefix: オニ"}, {"aliases": ["ORANGE JUICE BOX"], "pen_names": ["文月こーすけ"], "position": "F02", "links": ["http://x.com/koutyan7714"], "comments": "Kana prefix: オレ"}, {"aliases": ["おんがくはたのしい"], "pen_names": ["桃"], "position": "D11", "comments": "Kana prefix: オン"}, {"aliases": ["On Prism Records"], "pen_names": ["いるかアイス、市瀬るぽ"], "position": "B45.46", "links": ["http://onprism-rec.com/", "http://x.com/irucaice", "http://www.nicovideo.jp/user/86170431"], "comments": "Kana prefix: オン"}, {"aliases": ["廻転楕円体"], "pen_names": ["廻転楕円体"], "position": "B27.28", "links": ["https://kaitendaentai.com/", "http://x.com/kaitendaentai", "http://www.nicovideo.jp/user/49740856"], "comments": "Kana prefix: カイ"}, {"aliases": ["楓遥登"], "pen_names": ["楓遥登、ねぇねぇぼうや"], "position": "E31", "links": ["https://www.thr-musicoffice.com/", "http://x.com/kaedeharuto123", "http://www.pixiv.net/member.php?id=77196899"], "comments": "Kana prefix: カエ"}, {"aliases": ["篝竜太郎"], "pen_names": ["篝竜太郎"], "position": "C61", "links": ["https://lit.link/kagaryu", "http://x.com/kagari_ryutaro", "http://www.nicovideo.jp/user/123961918"], "comments": "Kana prefix: カガ"}, {"aliases": ["CAFFEINISM"], "pen_names": ["CAFFEIN"], "position": "E68", "links": ["http://caffein89.blogspot.jp/", "http://x.com/caffein89", "http://www.pixiv.net/member.php?id=13054"], "comments": "Kana prefix: カフ"}, {"aliases": ["Cafe Rainbird"], "pen_names": ["雨傘P"], "position": "D30", "links": ["https://caferainbird.nobody.jp/", "http://x.com/decoybird"], "comments": "Kana prefix: カフ"}, {"aliases": ["仮面商店街"], "pen_names": ["阿亀屋"], "position": "C03", "links": ["https://okameyasan.wixsite.com/records-net", "http://x.com/okameyasan", "http://www.nicovideo.jp/user/97365523"], "comments": "Kana prefix: カメ"}, {"aliases": ["我楽多スタジオ"], "pen_names": ["No.D"], "position": "D12", "links": ["https://garakutastudio.blog.ss-blog.jp/", "http://x.com/Numb_D"], "comments": "Kana prefix: ガラ"}, {"aliases": ["カラフルバブル"], "pen_names": ["はなぽ(わんわんP)"], "position": "D33", "links": ["https://colorfulbubble.net/", "http://x.com/hanapo_music", "http://www.nicovideo.jp/user/2821973"], "comments": "Kana prefix: カラ"}, {"aliases": ["がるなん.com"], "pen_names": ["ガルナ(オワタP)"], "position": "A24", "links": ["https://garunan.com/", "http://x.com/tomatowt", "http://www.nicovideo.jp/user/1320776"], "comments": "Kana prefix: ガル"}, {"aliases": ["完全1度。"], "pen_names": ["ただすけ"], "position": "E56", "links": ["http://uniloid.blog4.fc2.com/", "http://x.com/tada_sk", "http://www.pixiv.net/member.php?id=2647169"], "comments": "Kana prefix: カン"}, {"aliases": ["木賽のお宿"], "pen_names": ["ウッドダイスP"], "position": "F08", "links": ["http://x.com/woodDice_P", "http://www.nicovideo.jp/user/993967"], "comments": "Kana prefix: キサ"}, {"aliases": ["きさらんどりー"], "pen_names": ["きさら"], "position": "D73.74", "links": ["https://www.youtube.com/channel/UC49ZFh9hYLpHIN_UbL9wE0g", "http://x.com/kisalaundry"], "comments": "Kana prefix: キサ"}, {"aliases": ["キテとセリフの直売所"], "pen_names": ["キテ、セリフ"], "position": "W07.08", "links": ["http://nico.ms/sm39406933", "http://x.com/notata_kite", "http://www.pixiv.net/member.php?id=33917957"], "comments": "Kana prefix: キテ"}, {"aliases": ["KinosuKu×紅樂苑"], "pen_names": ["クスノキ、もみじ"], "position": "B25.26", "links": ["http://x.com/kusunokimizuha", "http://www.pixiv.net/member.php?id=34198299"], "comments": "Kana prefix: キノ"}, {"aliases": ["Gamble Loom"], "pen_names": ["Yamaji、匿名ゲルマ、大漠波新、キツネリ"], "position": "B05.06", "links": ["https://www.gambleloom.com/", "http://x.com/yamaji963"], "comments": "Kana prefix: ギャ"}, {"aliases": ["ギンユーシジン"], "pen_names": ["冴戒椎也"], "position": "D18", "links": ["https://ameblo.jp/shiiyasakai/", "http://x.com/sakaishiiya", "http://www.nicovideo.jp/user/2878420"], "comments": "Kana prefix: ギン"}, {"aliases": ["空想書架"], "pen_names": ["由末イリ、竹椅子"], "position": "D72", "links": ["http://ghostomeiris.wixsite.com/yuleiyashiki", "http://x.com/iri_qitune", "http://www.pixiv.net/member.php?id=33519225"], "comments": "Kana prefix: クウ"}, {"aliases": ["くすのせさんとこ"], "pen_names": ["くすのせ"], "position": "C37", "links": ["https://kusunose39.fanbox.cc/", "http://x.com/kusunose39", "http://www.pixiv.net/member.php?id=3351550"], "comments": "Kana prefix: クス"}, {"aliases": ["ぐちりずむ"], "pen_names": ["ぐちり"], "position": "B03.04", "links": ["https://bomless-race.theblog.me/", "http://x.com/bomless_race", "http://www.nicovideo.jp/user/16472555"], "comments": "Kana prefix: グチ"}, {"aliases": ["GOOD GRIEF RECORDS"], "pen_names": ["きゅおんママ"], "position": "D75.76", "links": ["https://www.youtube.com/channel/UCYNydPVhIGApnNp0upHbGRw", "http://x.com/sound9th", "http://www.pixiv.net/member.php?id=6308290"], "comments": "Kana prefix: グッ"}, {"aliases": ["ぐとぐと煮込みハンバーグ"], "pen_names": ["ぐりーん、灯遠"], "position": "D79", "links": ["http://x.com/Velvet_Prelude"], "comments": "Kana prefix: グト"}, {"aliases": ["熊吉くん"], "pen_names": ["mikuma"], "position": "F49", "links": ["http://x.com/3kMA7", "http://www.pixiv.net/member.php?id=4262043"], "comments": "Kana prefix: クマ"}, {"aliases": ["くら音工房"], "pen_names": ["くらね"], "position": "C02", "links": ["https://lit.link/clane", "http://x.com/clane_0112"], "comments": "Kana prefix: クラ"}, {"aliases": ["くるみるく"], "pen_names": ["medyum"], "position": "E53", "links": ["http://x.com/medyum_medyum", "http://www.pixiv.net/member.php?id=8500129"], "comments": "Kana prefix: クル"}, {"aliases": ["ClowZ劇場"], "pen_names": ["渡瀬しぃの、ちくわ◎"], "position": "F54", "links": ["http://x.com/Non7", "http://www.pixiv.net/member.php?id=1457047"], "comments": "Kana prefix: クロ"}, {"aliases": ["クロムジワークス"], "pen_names": ["クロムジ"], "position": "D71", "links": ["http://x.com/mujikuro", "http://www.pixiv.net/member.php?id=17219657"], "comments": "Kana prefix: クロ"}, {"aliases": ["ケチャップ販売員"], "pen_names": ["オゾン"], "position": "A11.12", "links": ["https://ozon541.wixsite.com/ozon541", "http://x.com/ozon_541", "http://www.nicovideo.jp/user/37280558"], "comments": "Kana prefix: ケチ"}, {"aliases": ["月面キャンバス"], "pen_names": ["ルナおじ"], "position": "F59.60", "links": ["http://x.com/runa_coretri", "http://www.pixiv.net/member.php?id=2074281"], "comments": "Kana prefix: ゲツ"}, {"aliases": ["限界保護区-BR01-"], "pen_names": ["ひき、与花"], "position": "F41.42", "links": ["http://x.com/turn3341", "http://www.pixiv.net/member.php?id=9167421"], "comments": "Kana prefix: ゲン"}, {"aliases": ["現在猫不足。"], "pen_names": ["彩"], "position": "F52", "links": ["http://x.com/hourai_24", "http://www.pixiv.net/member.php?id=6239144"], "comments": "Kana prefix: ゲン"}, {"aliases": ["光冬ノ社"], "pen_names": ["みぞれ ふゆき"], "position": "F64", "links": ["http://x.com/fuyukimizo0_abc", "http://www.pixiv.net/member.php?id=961943"], "comments": "Kana prefix: コウ"}, {"aliases": ["55ymtk"], "pen_names": ["55ymtk"], "position": "E19", "links": ["https://55ymtk.com/", "http://x.com/55ymtk", "http://www.pixiv.net/member.php?id=29287976"], "comments": "Kana prefix: ゴー"}, {"aliases": ["胡町屋"], "pen_names": ["胡町 吟"], "position": "E57", "links": ["http://x.com/komachi_gin"], "comments": "Kana prefix: コマ"}, {"aliases": ["KOMOS"], "pen_names": ["こもす"], "position": "F16", "links": ["https://komosu.booth.pm/", "http://x.com/ko_mosu", "http://www.pixiv.net/member.php?id=43663157"], "comments": "Kana prefix: コモ"}, {"aliases": ["こんぺいとう屋"], "pen_names": ["南 ぴぐ"], "position": "F18", "links": ["http://x.com/pigu2n", "http://www.pixiv.net/member.php?id=2112242"], "comments": "Kana prefix: コン"}, {"aliases": ["Cybernetic DIVA Lab."], "pen_names": ["DORAN"], "position": "E73", "links": ["https://doran3939.wordpress.com/", "http://x.com/dora_n_8239", "http://www.nicovideo.jp/user/16465393"], "comments": "Kana prefix: サイ"}, {"aliases": ["SOUTH."], "pen_names": ["南"], "position": "F25", "links": ["http://x.com/_373_island", "http://www.pixiv.net/member.php?id=3252451"], "comments": "Kana prefix: サウ"}, {"aliases": ["SoundstorM"], "pen_names": ["Yui Kamui"], "position": "E11", "links": ["https://www.nicovideo.jp/series/359999", "http://x.com/stormkamui", "http://www.pixiv.net/member.php?id=16628206"], "comments": "Kana prefix: サウ"}, {"aliases": ["Sound Stories by tk"], "pen_names": ["tk:タピオカP"], "position": "D04", "links": ["https://soundstoriesbytk.com/", "http://x.com/tk_tkhd", "http://www.nicovideo.jp/user/21009627"], "comments": "Kana prefix: サウ"}, {"aliases": ["Sound Horizirow"], "pen_names": ["堀次郎"], "position": "C51", "links": ["http://x.com/Horizirow", "http://www.pixiv.net/member.php?id=784121"], "comments": "Kana prefix: サウ"}, {"aliases": ["Saku"], "pen_names": ["Saku"], "position": "C47", "links": ["https://www.youtube.com/c/Sakuogt", "http://x.com/sakuogt"], "comments": "Kana prefix: サク"}, {"aliases": ["桜光房"], "pen_names": ["鷹音ソウ"], "position": "F27", "links": ["http://x.com/lukanescence", "http://www.pixiv.net/member.php?id=4338843"], "comments": "Kana prefix: サク"}, {"aliases": ["Sakura Perfume"], "pen_names": ["香咲さくら"], "position": "A31.32", "links": ["https://kasakisakura.wixsite.com/my-site", "http://x.com/KasakiSakura", "http://www.pixiv.net/member.php?id=32206157"], "comments": "Kana prefix: サク"}, {"aliases": ["ささらすぴん"], "pen_names": ["小金井ささら"], "position": "D54", "links": ["https://www.nicovideo.jp/mylist/29413293", "http://x.com/kgneissr", "http://www.pixiv.net/member.php?id=15444730"], "comments": "Kana prefix: ササ"}, {"aliases": ["さばパン"], "position": "E52", "links": ["http://profile.hatena.ne.jp/kyktwintail/", "http://x.com/KYK_twintail", "http://www.pixiv.net/member.php?id=3051477"], "comments": "Kana prefix: サバ"}, {"aliases": ["the heavenly yard"], "pen_names": ["mothy_悪ノP"], "position": "E01", "links": ["http://mothy.blog39.fc2.com", "http://x.com/mothy_akuno", "http://www.nicovideo.jp/user/907343"], "comments": "Kana prefix: ザヘ"}, {"aliases": ["五月雨"], "pen_names": ["サツキ"], "position": "D07", "links": ["http://x.com/32ki_may", "http://www.nicovideo.jp/user/88956260"], "comments": "Kana prefix: サミ"}, {"aliases": ["Samgyeopsal Records"], "pen_names": ["のうべんばあ TaDA"], "position": "E27.28", "links": ["http://youtube.com/channel/UC_EUCCZrdbCp60-CgMEXQLQ", "http://x.com/rinnnrine"], "comments": "Kana prefix: サム"}, {"aliases": ["39☆fantasy"], "pen_names": ["kyon-U"], "position": "F47.48", "links": ["http://x.com/kyon_u", "http://www.pixiv.net/member.php?id=2376936"], "comments": "Kana prefix: サン"}, {"aliases": ["サンシロー。"], "pen_names": ["サンシロー。"], "position": "D38", "links": ["http://x.com/sanshiro_jp"], "comments": "Kana prefix: サン"}, {"aliases": ["Seeka ."], "pen_names": ["Seeka . 有無"], "position": "B31.32", "links": ["http://www.youtube.com/channel/UCKoYJRq4OkD0vrWWvFqBhuQ", "http://x.com/Seeka_vocp816", "http://www.nicovideo.jp/user/117859463"], "comments": "Kana prefix: シー"}, {"aliases": ["G.C.M Records"], "pen_names": ["アンメルツP"], "position": "D15.16", "links": ["https://www.gcmstyle.com/", "http://x.com/gcmstyle", "http://www.pixiv.net/member.php?id=1100867"], "comments": "Kana prefix: ジー"}, {"aliases": ["C.C.C.C."], "pen_names": ["Camelots"], "position": "D70", "links": ["http://x.com/Camelots_Band"], "comments": "Kana prefix: シー"}, {"aliases": ["G.Roop -黒瓜丿美の部屋-"], "pen_names": ["黒瓜丿美"], "position": "E33", "links": ["https://amycrowley02.wixsite.com/groop", "http://x.com/G_Roop_", "http://www.nicovideo.jp/user/7203478"], "comments": "Kana prefix: ジー"}, {"aliases": ["siesta 歩く人の店"], "pen_names": ["歩く人"], "position": "A01.02", "links": ["https://www.youtube.com/c/pedestrianJPN", "http://x.com/tri_angl_e"], "comments": "Kana prefix: シエ"}, {"aliases": ["シカクドット"], "pen_names": ["シカクドット"], "position": "D44", "links": ["http://x.com/shikaku_dot"], "comments": "Kana prefix: シカ"}, {"aliases": ["頻る交サ点"], "pen_names": ["頻"], "position": "C04", "links": ["http://x.com/shi_ki_ri", "http://www.nicovideo.jp/user/65272146"], "comments": "Kana prefix: シキ"}, {"aliases": ["しぐのこ"], "pen_names": ["やつを、しぐれ、つちのこ"], "position": "F31.32", "links": ["http://x.com/yatsuwo_emiya"], "comments": "Kana prefix: シグ"}, {"aliases": ["地獄の馬"], "pen_names": ["パルモカ"], "position": "C52", "links": ["http://x.com/pppsh_mk"], "comments": "Kana prefix: ジゴ"}, {"aliases": ["獅子兎レコーズ"], "pen_names": ["シシド"], "position": "B39.40", "links": ["http://linktr.ee/shishido_4410", "http://x.com/shishido_4410", "http://www.pixiv.net/member.php?id=38757554"], "comments": "Kana prefix: シシ"}, {"aliases": ["System Corruption"], "pen_names": ["リオネ"], "position": "D65", "links": ["http://x.com/gra_byte"], "comments": "Kana prefix: シス"}, {"aliases": ["試聴履歴"], "pen_names": ["みとう。 inuha"], "position": "C21", "links": ["http://x.com/mitou119"], "comments": "Kana prefix: シチ"}, {"aliases": ["Citrus*Love it"], "pen_names": ["兎神架聖、みかん色のひと"], "position": "F04", "links": ["http://x.com/24mikan_iro", "http://www.nicovideo.jp/user/405657"], "comments": "Kana prefix: シト"}, {"aliases": ["shino"], "pen_names": ["shino"], "position": "B50", "links": ["https://www.youtube.com/channel/UCLd0VGHm6RXx3_qKqwIQ2zA", "http://x.com/shi_no_music"], "comments": "Kana prefix: シノ"}, {"aliases": ["縞城のおしろ"], "pen_names": ["縞城 依月"], "position": "A29.30", "links": ["https://www.pixiv.net/users/8543545", "http://x.com/p_2k", "http://www.pixiv.net/member.php?id=8543545"], "comments": "Kana prefix: シマ"}, {"aliases": ["社会参加東京流通センター支部"], "pen_names": ["ゆきち"], "position": "C25", "links": ["http://x.com/kimasirawa"], "comments": "Kana prefix: シャ"}, {"aliases": ["じゃむステーション"], "pen_names": ["じゃむ"], "position": "F46", "links": ["http://x.com/jam3939_shaker", "http://www.pixiv.net/member.php?id=29222715"], "comments": "Kana prefix: ジャ"}, {"aliases": ["食物図鑑"], "pen_names": ["羊歯食物"], "position": "C45", "links": ["https://www.nicovideo.jp/my/mylist/73060034?ref=pc_mypage_mylist", "http://x.com/shidashoku"], "comments": "Kana prefix: ショ"}, {"aliases": ["白神さん家"], "pen_names": ["白神大輝"], "position": "C10", "links": ["http://www.shiragasanchi.com", "http://x.com/shiraga97"], "comments": "Kana prefix: シラ"}, {"aliases": ["私立ボカロP学園初等部"], "pen_names": ["Shu、音無あふ、rukaku"], "position": "W05.06", "links": ["https://vocagaku.jimdofree.com/", "http://x.com/shu_horiike", "http://www.nicovideo.jp/user/116289713"], "comments": "Kana prefix: シリ"}, {"aliases": ["シロクマ探検隊"], "pen_names": ["しろくま。"], "position": "C09", "links": ["http://x.com/kazuna_w_bear"], "comments": "Kana prefix: シロ"}, {"aliases": ["白黒世界"], "pen_names": ["白黒世界P"], "position": "D32", "links": ["https://www.youtube.com/channel/UCsv52b8bRhV7zwiDtC27RAQ", "http://x.com/SKworldofficial"], "comments": "Kana prefix: シロ"}, {"aliases": ["しろしぐだう!!!"], "pen_names": ["しろくろ、しぐぽん、だうあ"], "position": "F39.40", "links": ["http://x.com/shirokuro_3939"], "comments": "Kana prefix: シロ"}, {"aliases": ["ジヲン・グンソグ"], "pen_names": ["紫煮 染グ、ジヲ"], "position": "D49.50", "links": ["http://x.com/sini_isogu"], "comments": "Kana prefix: ジヲ"}, {"aliases": ["Sincerely Syncopation"], "pen_names": ["ねこぜなおとこ"], "position": "D06", "links": ["https://www.youtube.com/channel/UCHcSJWHQOpywdNmsn0fXYPQ", "http://x.com/697nekoze", "http://www.nicovideo.jp/user/3575359"], "comments": "Kana prefix: シン"}, {"aliases": ["すいくれどっとこむ"], "pen_names": ["翠久怜音、神山春也"], "position": "D48", "links": ["http://x.com/Lain_di0pkh"], "comments": "Kana prefix: スイ"}, {"aliases": ["Studio Ark Attack"], "pen_names": ["ぼーかりおどP(noa)"], "position": "A27", "links": ["http://vocaliod.blog54.fc2.com/", "http://x.com/vocaliod_P", "http://www.pixiv.net/member.php?id=1143244"], "comments": "Kana prefix: スタ"}, {"aliases": ["StudioGnu"], "pen_names": ["椎乃味醂、柚璃遥"], "position": "B11.12", "links": ["https://www.youtube.com/channel/UC_P7NBqY_sWRjWcGeUWMVWA/featured", "http://x.com/sheeno3rin", "http://www.nicovideo.jp/user/66296951"], "comments": "Kana prefix: スタ"}, {"aliases": ["STUDIO 440"], "pen_names": ["杉山U1"], "position": "D34", "links": ["https://ccmarurecords.wordpress.com/", "http://x.com/theS_O_L"], "comments": "Kana prefix: スタ"}, {"aliases": ["Studio SHIRAKABA"], "pen_names": ["asanuko"], "position": "C17", "links": ["http://x.com/asanuko"], "comments": "Kana prefix: スタ"}, {"aliases": ["studioMURASAKI"], "pen_names": ["MURASAKI"], "position": "D27", "links": ["https://lit.link/yukarinmurasaki", "http://x.com/yukarinmurasaki"], "comments": "Kana prefix: スタ"}, {"aliases": ["すたろんはいどあうと"], "pen_names": ["すたすたろん"], "position": "D62", "links": ["https://www.youtube.com/channel/UCOfsL_alsh1Ai0iOYIxScKg", "http://x.com/Sutasutasutaron"], "comments": "Kana prefix: スタ"}, {"aliases": ["Stripeless"], "pen_names": ["しま"], "position": "B56", "links": ["https://stripeless.net/", "http://x.com/shima_10shi", "http://www.nicovideo.jp/user/21858097"], "comments": "Kana prefix: スト"}, {"aliases": ["スナレフの村"], "pen_names": ["沙レフ"], "position": "C12", "links": ["http://x.com/sunarefu3702"], "comments": "Kana prefix: スナ"}, {"aliases": ["スパイダーとmilano"], "pen_names": ["スパイダーっちょ"], "position": "D31", "links": ["https://dama66666.fanbox.cc/", "http://x.com/dama66666", "http://www.nicovideo.jp/user/88974"], "comments": "Kana prefix: スパ"}, {"aliases": ["#1501"], "pen_names": ["Icchi、souI"], "position": "D19.20", "links": ["https://icchi1501.wixsite.com/1501officialhomepage", "http://x.com/Icchi1501", "http://www.nicovideo.jp/user/54306124"], "comments": "Kana prefix: スプ"}, {"aliases": ["SPACELECTRO"], "pen_names": ["SPACELECTRO"], "position": "A22", "links": ["http://spacelectro.com/", "http://x.com/Spacelectro", "http://www.pixiv.net/member.php?id=18389013"], "comments": "Kana prefix: スペ"}, {"aliases": ["墨眼茶屋"], "pen_names": ["墨之 御南"], "position": "E43.44", "links": ["http://x.com/sumimeno", "http://www.pixiv.net/member.php?id=36891018"], "comments": "Kana prefix: スミ"}, {"aliases": ["suragi"], "pen_names": ["suragi"], "position": "C26", "links": ["http://x.com/suragi2196"], "comments": "Kana prefix: スラ"}, {"aliases": ["スリーマンセル"], "pen_names": ["やみくろ、挫折P、いもすけ"], "position": "D03", "links": ["https://www.youtube.com/channel/UCW5WhuDqzCzrb1IDNyo7IMQ", "http://x.com/yamichrome"], "comments": "Kana prefix: スリ"}, {"aliases": ["せなのまど(瀬名航)"], "pen_names": ["瀬名航"], "position": "E15.16", "links": ["http://www.senawataru.com/", "http://x.com/wataru_sena"], "comments": "Kana prefix: セナ"}, {"aliases": ["SOUDA!"], "pen_names": ["そうだ"], "position": "D29", "links": ["https://pixiv.me/jajajajaaaan", "http://x.com/so0uda", "http://www.pixiv.net/member.php?id=3867830"], "comments": "Kana prefix: ソウ"}, {"aliases": ["そらのかがみ"], "pen_names": ["たかのアキ"], "position": "E55", "links": ["https://wp.me/P87Tgw-E", "http://x.com/E_takano_aki", "http://www.pixiv.net/member.php?id=738720"], "comments": "Kana prefix: ソラ"}, {"aliases": ["solidbeats"], "pen_names": ["Re:nG"], "position": "A17.18", "links": ["https://reng.jp/", "http://x.com/_reng"], "comments": "Kana prefix: ソリ"}, {"aliases": ["たけねこれこーず"], "pen_names": ["タケノコ少年"], "position": "A03.04", "links": ["https://www.youtube.com/channel/UCmJ4De_H9aSnDDxGKcrpwCw", "http://x.com/ta_mor_i", "http://www.pixiv.net/member.php?id=18698284"], "comments": "Kana prefix: タケ"}, {"aliases": ["立椅子かんなと皆川溺"], "pen_names": ["皆川溺 立椅子かんな"], "position": "B35.36", "links": ["http://x.com/23dimensionsP"], "comments": "Kana prefix: タテ"}, {"aliases": ["たのしい生物のじかん"], "pen_names": ["unui"], "position": "D28", "links": ["https://note.com/unui/", "http://x.com/unui", "http://www.pixiv.net/member.php?id=2814002"], "comments": "Kana prefix: タノ"}, {"aliases": ["だるまや"], "pen_names": ["Dharma"], "position": "E13", "links": ["http://x.com/KurzweilMaster", "http://www.pixiv.net/member.php?id=1057033"], "comments": "Kana prefix: ダル"}, {"aliases": ["CHINIYA MUSIC"], "pen_names": ["ラキヤP"], "position": "D80", "links": ["http://x.com/circlevil", "http://www.nicovideo.jp/user/92314486"], "comments": "Kana prefix: チニ"}, {"aliases": ["地這組"], "pen_names": ["オバキオ、ギンクル、タルジオ、ツンデレ"], "position": "C43.44", "links": ["http://x.com/obakioP"], "comments": "Kana prefix: チハ"}, {"aliases": ["childeyes"], "pen_names": ["境ヶ原まるこ"], "position": "E49", "links": ["http://x.com/propellerwalker", "http://www.pixiv.net/member.php?id=650344"], "comments": "Kana prefix: チャ"}, {"aliases": ["ちりそめレコード"], "pen_names": ["そめし"], "position": "C35", "links": ["http://www.nicovideo.jp/mylist/49743994", "http://x.com/chirisomeshi", "http://www.nicovideo.jp/user/45150091"], "comments": "Kana prefix: チリ"}, {"aliases": ["Twinfield"], "pen_names": ["Twinfield"], "position": "B51", "links": ["https://lit.link/twinfield", "http://x.com/Twinfieldnex", "http://www.pixiv.net/member.php?id=22518049"], "comments": "Kana prefix: ツイ"}, {"aliases": ["月のしるし"], "pen_names": ["るなまーく"], "position": "F26", "links": ["https://lunamark-archives.tumblr.com/", "http://x.com/lunamark00", "http://www.pixiv.net/member.php?id=179014"], "comments": "Kana prefix: ツキ"}, {"aliases": ["つきみぐー、"], "pen_names": ["つきみぐー、"], "position": "C29", "links": ["https://www.youtube.com/c/tsukimizzz_original", "http://x.com/tsukimizzz", "http://www.pixiv.net/member.php?id=24534110"], "comments": "Kana prefix: ツキ"}, {"aliases": ["TEARDROP RECORDS"], "pen_names": ["rakurui"], "position": "C19", "links": ["https://rakurui.jimdofree.com", "http://x.com/rakurui_t", "http://www.nicovideo.jp/user/6473451"], "comments": "Kana prefix: ティ"}, {"aliases": ["Teary Planet"], "pen_names": ["Nanao，Youli，Chio"], "position": "B21.22", "links": ["http://x.com/Teary_Planet", "http://www.nicovideo.jp/user/25689813"], "comments": "Kana prefix: ティ"}, {"aliases": ["TK.FACTORY"], "pen_names": ["竹工房"], "position": "F21.22", "links": ["http://x.com/TkFactory19", "http://www.nicovideo.jp/user/4463489"], "comments": "Kana prefix: ティ"}, {"aliases": ["DIVELA"], "pen_names": ["DIVELA"], "position": "B60", "links": ["https://www.youtube.com/channel/UCrGzu0MPKQpYF2AV2oG-VpQ", "http://x.com/MIX_Destroy", "http://www.nicovideo.jp/user/30201787"], "comments": "Kana prefix: ディ"}, {"aliases": ["This is a cat."], "pen_names": ["こがねむし、ねこから"], "position": "C31", "links": ["http://korehaneko.com", "http://x.com/blackteabisco", "http://www.nicovideo.jp/user/17435673"], "comments": "Kana prefix: ディ"}, {"aliases": ["テクテク旅団"], "pen_names": ["はかめ"], "position": "W09.10", "links": ["http://x.com/ktnazm0702"], "comments": "Kana prefix: テク"}, {"aliases": ["Desk Top Mikan"], "pen_names": ["Torque、HotαRu、Miwo"], "position": "B59", "links": ["http://x.com/torque96k", "http://www.nicovideo.jp/user/75254649"], "comments": "Kana prefix: デス"}, {"aliases": ["鉄道集本部"], "pen_names": ["こういち"], "position": "E69", "links": ["http://tetsumoe.web.fc2.com/index.html", "http://x.com/jikan_zuidou", "http://www.pixiv.net/member.php?id=3685167"], "comments": "Kana prefix: テツ"}, {"aliases": ["天気、のきのき?"], "pen_names": ["efueichi、ウル"], "position": "D53", "links": ["https://www.youtube.com/channel/UC18x1sHUWwEa6DkYgaiU3tA", "http://x.com/FH1776"], "comments": "Kana prefix: テン"}, {"aliases": ["電脳戯画TOKYO出張編"], "pen_names": ["ichica、KICO"], "position": "D09", "links": ["https://www.youtube.com/channel/UC5uWXKYENGC1jh2f1hkzDiw", "http://x.com/ichi_ft"], "comments": "Kana prefix: デン"}, {"aliases": ["twinkledisc"], "pen_names": ["Dios/シグナルP"], "position": "A21", "links": ["https://twinkledisc.net", "http://x.com/Hiroaki_Arai_", "http://www.pixiv.net/member.php?id=542786"], "comments": "Kana prefix: トゥ"}, {"aliases": ["Togo"], "pen_names": ["Togo"], "position": "C14", "links": ["https://linktr.ee/togo_", "http://x.com/Togo_105_"], "comments": "Kana prefix: トウ"}, {"aliases": ["東京MARCOPOLO"], "pen_names": ["ハジメ優"], "position": "C23", "links": ["https://www.youtube.com/c/tokyo-mp", "http://x.com/marcopolo_tokyo"], "comments": "Kana prefix: トー"}, {"aliases": ["どーなつとんねる"], "pen_names": ["御坂しゃの"], "position": "C07", "links": ["https://www.nicovideo.jp/mylist/73745730", "http://x.com/shanoneco", "http://www.nicovideo.jp/user/125514215"], "comments": "Kana prefix: ドー"}, {"aliases": ["TtoitR"], "pen_names": ["樽"], "position": "E71", "links": ["https://evilliousfgoperati.wixsite.com/evilliousfg", "http://x.com/tarut52124", "http://www.pixiv.net/member.php?id=9966721"], "comments": "Kana prefix: トト"}, {"aliases": ["飛梅レコーズ"], "pen_names": ["らしゅりー 束子屋コウ ヲタ乙"], "position": "B29.30", "links": ["https://tobiumerec.tumblr.com/", "http://x.com/rashlyman", "http://www.nicovideo.jp/user/1373448"], "comments": "Kana prefix: トビ"}, {"aliases": ["DNBS"], "pen_names": ["REI"], "position": "C20", "links": ["http://x.com/CafeKareido1245"], "comments": "Kana prefix: ドラ"}, {"aliases": ["TreatHunters×ろますと部"], "pen_names": ["野中ハロウィン"], "position": "E09.10", "links": ["http://x.com/jirai_bugtsune", "http://www.nicovideo.jp/user/57684453"], "comments": "Kana prefix: トリ"}, {"aliases": ["Drawing Kanon"], "pen_names": ["奏音"], "position": "F07", "links": ["http://x.com/kanon_mikukanon", "http://www.pixiv.net/member.php?id=34444704"], "comments": "Kana prefix: ドロ"}, {"aliases": ["とんびとならせ"], "pen_names": ["奈良瀬、Tonbi"], "position": "C53.54", "links": ["http://x.com/narase_05"], "comments": "Kana prefix: トン"}, {"aliases": ["中野ゆの"], "pen_names": ["中野ゆの"], "position": "B19.20", "links": ["http://x.com/yunoatto", "http://www.pixiv.net/member.php?id=30277130"], "comments": "Kana prefix: ナカ"}, {"aliases": ["なきそ堂"], "pen_names": ["なきそ"], "position": "W21.22", "links": ["http://x.com/7kiso_nakiso"], "comments": "Kana prefix: ナキ"}, {"aliases": ["名古屋県民"], "pen_names": ["ムラタシユウ、Tokaya"], "position": "B41.42", "links": ["http://x.com/muratashiyuu"], "comments": "Kana prefix: ナゴ"}, {"aliases": ["いつか必ずなにか成すの会"], "pen_names": ["サドヤ、スミア、ヒトゴト、ソデノアラワ"], "position": "W15.16", "links": ["https://sadoyaa.wixsite.com/nasukai", "http://x.com/nanikanasu"], "comments": "Kana prefix: ナス"}, {"aliases": ["____natural"], "pen_names": ["____natural"], "position": "E07", "links": ["https://www.youtube.com/channel/UCCcTq2NJXJ6xl37ivEsV7Fg/featured?view_as=subscriber", "http://x.com/____natural"], "comments": "Kana prefix: ナチ"}, {"aliases": ["夏樹"], "pen_names": ["夏樹"], "position": "E23", "links": ["http://x.com/mn20nm16siguma"], "comments": "Kana prefix: ナツ"}, {"aliases": ["なりょーのおみやげやさん"], "pen_names": ["成宮 亮"], "position": "D01", "links": ["http://x.com/naryo_1008"], "comments": "Kana prefix: ナリ"}, {"aliases": ["No.09"], "pen_names": ["雨曇"], "position": "E25.26", "links": ["http://x.com/Rain_C13"], "comments": "Kana prefix: ナン"}, {"aliases": ["2389円の氷菓子"], "pen_names": ["氷菓子(カナ)"], "position": "F57", "links": ["http://x.com/23_kana_89", "http://www.pixiv.net/member.php?id=3993525"], "comments": "Kana prefix: ニセ"}, {"aliases": ["にんかん丼"], "pen_names": ["えしぇみる"], "position": "F51", "links": ["http://x.com/eshe_mr", "http://www.pixiv.net/member.php?id=7665656"], "comments": "Kana prefix: ニン"}, {"aliases": ["ねいろずむ"], "pen_names": ["祢衣"], "position": "F28", "links": ["https://neirozum.tumblr.com/", "http://x.com/neirozum", "http://www.pixiv.net/member.php?id=9991725"], "comments": "Kana prefix: ネイ"}, {"aliases": ["ネギシャワーP VS. ゴジラの吐息"], "pen_names": ["ネギシャワーP、ゴジラの吐息"], "position": "B23.24", "links": ["https://www.negishower.com/", "http://x.com/kaga_qwerty"], "comments": "Kana prefix: ネギ"}, {"aliases": ["Negi☆Lee(a)ks!!"], "pen_names": ["茶碗蒸し、あるるさん"], "position": "F03", "links": ["https://negi-link.com/negi/", "http://x.com/Negi_Leeks", "http://www.pixiv.net/member.php?id=29128511"], "comments": "Kana prefix: ネギ"}, {"aliases": ["NEXTLIGHT"], "pen_names": ["Reno、picco"], "position": "B01.02", "links": ["https://twitter.com/nextlight_jp", "http://x.com/picco_xxx", "http://www.nicovideo.jp/user/68044045"], "comments": "Kana prefix: ネク"}, {"aliases": ["ねこしゃん"], "pen_names": ["SEE、桜餅ルナ"], "position": "D67.68", "links": ["http://x.com/senlalowns", "http://www.nicovideo.jp/user/50828693"], "comments": "Kana prefix: ネコ"}, {"aliases": ["猫に生まれかわりたい"], "pen_names": ["ねむけのかたまり"], "position": "F33.34", "links": ["http://x.com/NEMUKE4869", "http://www.pixiv.net/member.php?id=49732453"], "comments": "Kana prefix: ネコ"}, {"aliases": ["ねころぶいぬ"], "pen_names": ["甘夏なか"], "position": "E66", "links": ["http://kanak-815.tumblr.com/", "http://x.com/knk_815", "http://www.pixiv.net/member.php?id=15027411"], "comments": "Kana prefix: ネコ"}, {"aliases": ["ねじ式"], "pen_names": ["ねじ式"], "position": "A05.06", "links": ["http://nejishiki.com", "http://x.com/nejishiki0221", "http://www.pixiv.net/member.php?id=8218839"], "comments": "Kana prefix: ネジ"}, {"aliases": ["年長組コンピ製作委員会"], "pen_names": ["佐倉井朔夜"], "position": "D14", "links": ["https://korundum-mkcp.tumblr.com/", "http://x.com/mk_compi"], "comments": "Kana prefix: ネン"}, {"aliases": ["ノイ&ナサガシ"], "pen_names": ["ノイ、ナサガシ"], "position": "B37.38", "links": ["https://www.youtube.com/channel/UC3GzkuHZNanJZQZml4Wte5A", "http://x.com/n0yn0yn0y"], "comments": "Kana prefix: ノイ"}, {"aliases": ["野猫堂"], "pen_names": ["NoNe"], "position": "F43", "links": ["http://x.com/NoNeon319", "http://www.pixiv.net/member.php?id=35308998"], "comments": "Kana prefix: ノネ"}, {"aliases": ["NoViLholic"], "pen_names": ["野蒜"], "position": "C32", "links": ["http://x.com/NowVillage0606"], "comments": "Kana prefix: ノビ"}, {"aliases": ["のりっこ弁当"], "pen_names": ["のりっこ"], "position": "F62", "links": ["http://x.com/norikkonori", "http://www.pixiv.net/member.php?id=33308408"], "comments": "Kana prefix: ノリ"}, {"aliases": ["のろしれこぉず"], "pen_names": ["げんぶ"], "position": "E20", "links": ["http://x.com/genbokaro"], "comments": "Kana prefix: ノロ"}, {"aliases": ["呑気な露店"], "pen_names": ["呑み気"], "position": "E67", "links": ["http://x.com/ikuzonomiki12", "http://www.pixiv.net/member.php?id=20645313"], "comments": "Kana prefix: ノン"}, {"aliases": ["ハイドランジア"], "pen_names": ["小紫花"], "position": "D61", "links": ["https://potofu.me/oshi87", "http://x.com/oshi_87", "http://www.nicovideo.jp/user/13733329"], "comments": "Kana prefix: ハイ"}, {"aliases": ["ハガネノウサギゴヤ"], "pen_names": ["赤兎かい"], "position": "D55.56", "links": ["http://ironrabbit.jpn.org/", "http://x.com/heatmetalx", "http://www.pixiv.net/member.php?id=9167808"], "comments": "Kana prefix: ハガ"}, {"aliases": ["baku"], "pen_names": ["baku"], "position": "C36", "links": ["http://x.com/tlgpda"], "comments": "Kana prefix: バク"}, {"aliases": ["HakoBook"], "position": "企01", "links": ["https://hakobook.com/", "http://x.com/hako_book"], "comments": "Kana prefix: ハコ"}, {"aliases": ["はしるらーめん"], "pen_names": ["けいそー"], "position": "E51", "links": ["http://x.com/keiso73", "http://www.pixiv.net/member.php?id=6141348"], "comments": "Kana prefix: ハシ"}, {"aliases": ["蓮実えれな"], "pen_names": ["蓮実えれな"], "position": "C06", "links": ["http://x.com/elena_hasumi"], "comments": "Kana prefix: ハス"}, {"aliases": ["はすみの春の日"], "pen_names": ["hasumi"], "position": "D37", "links": ["http://x.com/hasutsrk", "http://www.nicovideo.jp/user/93272531"], "comments": "Kana prefix: ハス"}, {"aliases": ["バターサンド"], "pen_names": ["バターサンド"], "position": "B53", "links": ["https://www.tabutterso.com", "http://x.com/TaButterSo"], "comments": "Kana prefix: バタ"}, {"aliases": ["＃ふぃぐます会 ボーマス支店"], "pen_names": ["アイ.figmaster"], "position": "F06", "links": ["http://x.com/sakinemeiko0006"], "comments": "Kana prefix: ハッ"}, {"aliases": ["ハナカセ本舗"], "pen_names": ["黒萩 涼"], "position": "E61.62", "links": ["http://x.com/kurohagiryo", "http://www.pixiv.net/member.php?id=170062"], "comments": "Kana prefix: ハナ"}, {"aliases": ["花結い"], "pen_names": ["青井ゆい"], "position": "F37.38", "links": ["https://1030aoiyui.wixsite.com/my-site-2/about", "http://x.com/1030Aoiyui", "http://www.pixiv.net/member.php?id=6445700"], "comments": "Kana prefix: ハナ"}, {"aliases": ["ハヤカワ・ラボ"], "pen_names": ["ハヤカワP"], "position": "E12", "links": ["https://note.com/plutonius/", "http://www.nicovideo.jp/user/1525541"], "comments": "Kana prefix: ハヤ"}, {"aliases": ["PICTURE BLUE"], "pen_names": ["Little Tanioka"], "position": "C40", "links": ["http://x.com/lil_tanioka"], "comments": "Kana prefix: ピク"}, {"aliases": ["HISAQUA"], "pen_names": ["AQUA / hisako"], "position": "B33.34", "links": ["https://hisaqua.booth.pm/", "http://x.com/aqua_ix", "http://www.nicovideo.jp/user/25130922"], "comments": "Kana prefix: ヒサ"}, {"aliases": ["Pizuya's Cell"], "pen_names": ["pizuya"], "position": "A19.20", "links": ["https://pizuya.com", "http://x.com/pizuya"], "comments": "Kana prefix: ピズ"}, {"aliases": ["hito"], "pen_names": ["hito"], "position": "D08", "links": ["http://x.com/rio_oir0", "http://www.nicovideo.jp/user/89497135"], "comments": "Kana prefix: ヒト"}, {"aliases": ["105ctのエメラルド"], "pen_names": ["碧亀"], "position": "D22", "links": ["https://emerald105turtle.wixsite.com/emerald105", "http://x.com/midori_game_105"], "comments": "Kana prefix: ヒャ"}, {"aliases": ["Vintage"], "pen_names": ["Vintage"], "position": "D45", "links": ["http://x.com/VintageKakudori", "http://www.pixiv.net/member.php?id=53794904"], "comments": "Kana prefix: ビン"}, {"aliases": ["First Ever ArCade"], "pen_names": ["夏山よつぎ、由末イリ、Iceky、他"], "position": "A15.16", "links": ["http://x.com/seckarium"], "comments": "Kana prefix: ファ"}, {"aliases": ["PHASESHIFT"], "pen_names": ["若葉 昌輝"], "position": "F05", "links": ["http://www1.plala.or.jp/wakaba/index_old.html", "http://x.com/masaki_wakaba", "http://www.pixiv.net/member.php?id=365280"], "comments": "Kana prefix: フェ"}, {"aliases": ["Form Change"], "pen_names": ["疾風389"], "position": "E47", "links": ["http://x.com/sippuu2", "http://www.pixiv.net/member.php?id=5340947"], "comments": "Kana prefix: フォ"}, {"aliases": ["ふがしやさん"], "pen_names": ["Sa-fu"], "position": "E59.60", "links": ["http://x.com/sfmk39", "http://www.pixiv.net/member.php?id=77915733"], "comments": "Kana prefix: フガ"}, {"aliases": ["ふかひれまかろん"], "pen_names": ["星月みこと、AYU"], "position": "F30", "links": ["http://x.com/miko_nico22"], "comments": "Kana prefix: フカ"}, {"aliases": ["フミヅキレコーズ"], "pen_names": ["文月フミト"], "position": "D63.64", "links": ["https://fumito-fumizuki.com", "http://x.com/fumito_fumizuki", "http://www.nicovideo.jp/user/69494009"], "comments": "Kana prefix: フミ"}, {"aliases": ["Blatantly Emotional Records"], "pen_names": ["書店太郎"], "position": "D25.26", "links": ["https://www.youtube.com/c/BlatantlyEmotionalRecords", "http://x.com/shotenteki_ore"], "comments": "Kana prefix: ブラ"}, {"aliases": ["フララTONE"], "pen_names": ["ティキ森 フララ"], "position": "C42", "links": ["https://www.youtube.com/channel/UCerUO324UHKfUERrcBEPdgA", "http://x.com/hulala_tiki"], "comments": "Kana prefix: フラ"}, {"aliases": ["bluto"], "position": "C60", "links": ["https://www.nicovideo.jp/mylist/73580161", "http://x.com/bluto_ebifry"], "comments": "Kana prefix: ブル"}, {"aliases": ["Fullunagi Records"], "pen_names": ["フルナギネヲ"], "position": "C38", "links": ["https://fullunagineo.wixsite.com/-site", "http://x.com/j_neo_p", "http://www.nicovideo.jp/user/120743405"], "comments": "Kana prefix: フル"}, {"aliases": ["Fluorite"], "pen_names": ["群咲たくみ"], "position": "C62", "links": ["https://akatoao.themedia.jp/", "http://x.com/akatoaoao", "http://www.nicovideo.jp/user/25963085"], "comments": "Kana prefix: フロ"}, {"aliases": ["forute|フヲルテ"], "pen_names": ["forute|フヲルテ"], "position": "C01", "links": ["https://www.youtube.com/channel/UC_06CYaApVGIP4cEykuZRDQ", "http://x.com/forute723", "http://www.nicovideo.jp/user/37661986"], "comments": "Kana prefix: フヲ"}, {"aliases": ["FUNBARECORDS"], "pen_names": ["カンパニュラ"], "position": "C58", "links": ["https://www.nicovideo.jp/mylist/64006320", "http://x.com/hanatootya", "http://www.nicovideo.jp/user/85293487"], "comments": "Kana prefix: フン"}, {"aliases": ["へち＊まころん"], "pen_names": ["へち"], "position": "E54", "links": ["http://x.com/hechi6_6", "http://www.pixiv.net/member.php?id=2675855"], "comments": "Kana prefix: ヘチ"}, {"aliases": ["ヘッドフォンガール"], "pen_names": ["カナタジュン"], "position": "C22", "links": ["https://hpg.booth.pm/", "http://x.com/junkanata"], "comments": "Kana prefix: ヘッ"}, {"aliases": ["ペポン商店"], "pen_names": ["ぺぽよ"], "position": "E39.40", "links": ["https://www.poyopep.com/", "http://x.com/pepoyoPPY", "http://www.pixiv.net/member.php?id=6592374"], "comments": "Kana prefix: ペポ"}, {"aliases": ["ベリーイージー"], "pen_names": ["EasyPop"], "position": "D41.42", "links": ["http://easypop.jp", "http://x.com/easypop_betti"], "comments": "Kana prefix: ベリ"}, {"aliases": ["変態機械"], "pen_names": ["Deino"], "position": "F35.36", "links": ["http://www.youtube.com/playlist?list=PL1D8C0E7D4ECBCCB3", "http://x.com/Deino", "http://www.pixiv.net/member.php?id=44588"], "comments": "Kana prefix: ヘン"}, {"aliases": ["忘却書店"], "pen_names": ["コウ、Kakeru、rins、ショウ"], "position": "E37.38", "links": ["https://www.youtube.com/diarays", "http://x.com/kou___________", "http://www.nicovideo.jp/user/22711505"], "comments": "Kana prefix: ボウ"}, {"aliases": ["ホシカケラごはん"], "pen_names": ["ガナスタ"], "position": "E48", "links": ["http://x.com/GANAMIKU_ANGEL", "http://www.pixiv.net/member.php?id=7292660"], "comments": "Kana prefix: ホシ"}, {"aliases": ["ほしがりりっく"], "pen_names": ["Naoto@ほしがりP"], "position": "C13", "links": ["http://x.com/Naoto_7010N"], "comments": "Kana prefix: ホシ"}, {"aliases": ["星屑屋"], "pen_names": ["wiLu、咲暗ちうね、ちゃんまんじ"], "position": "C05", "links": ["http://x.com/willwiLu"], "comments": "Kana prefix: ホシ"}, {"aliases": ["星乃神宮"], "pen_names": ["ホシミヤ"], "position": "D77.78", "links": ["https://vermilionstar0508.wixsite.com/hosimiya-star", "http://x.com/hosimiya_star"], "comments": "Kana prefix: ホシ"}, {"aliases": ["星のちくじら"], "pen_names": ["mochi"], "position": "E58", "links": ["http://x.com/mochityoko", "http://www.pixiv.net/member.php?id=16259144"], "comments": "Kana prefix: ホシ"}, {"aliases": ["Popism"], "pen_names": ["tekalu、Capchii"], "position": "B43.44", "links": ["http://x.com/tekalu_music"], "comments": "Kana prefix: ポッ"}, {"aliases": ["HOYOHOYO"], "pen_names": ["たかくら"], "position": "F19", "links": ["https://potofu.me/mug0u0", "http://x.com/mug_0u0", "http://www.pixiv.net/member.php?id=37894326"], "comments": "Kana prefix: ホヨ"}, {"aliases": ["Horizon Color"], "pen_names": ["あいおいゆうな"], "position": "E63", "links": ["http://x.com/mugicha6", "http://www.nicovideo.jp/user/4036814"], "comments": "Kana prefix: ホラ"}, {"aliases": ["PolyphonicBranch / ぽりふぉ"], "pen_names": ["ぽりふぉ"], "position": "A09.10", "links": ["http://polyphonicbranch.com", "http://x.com/Tomoya_PB"], "comments": "Kana prefix: ポリ"}, {"aliases": ["MY SHIP"], "pen_names": ["BCNO"], "position": "B13.14", "links": ["https://www.youtube.com/c/BCNO01", "http://x.com/bcno01", "http://www.nicovideo.jp/user/56254919"], "comments": "Kana prefix: マイ"}, {"aliases": ["MY SONG IS SHIT"], "pen_names": ["鬱P"], "position": "A25", "links": ["http://x.com/asshole_wii", "http://www.nicovideo.jp/user/176618"], "comments": "Kana prefix: マイ"}, {"aliases": ["毎日ハイカロリー"], "pen_names": ["もそ4"], "position": "F50", "links": ["http://x.com/moso4hc", "http://www.pixiv.net/member.php?id=67563404"], "comments": "Kana prefix: マイ"}, {"aliases": ["まぐろとねぎ"], "pen_names": ["望月 浅"], "position": "E42", "links": ["http://x.com/MikuLuka_negi", "http://www.pixiv.net/member.php?id=2643488"], "comments": "Kana prefix: マグ"}, {"aliases": ["MASK"], "pen_names": ["南ノ南、Adeliae、しゃいと、木瀬のん"], "position": "B07.08", "links": ["https://lit.link/maskvocaloid", "http://x.com/mnmno373", "http://www.pixiv.net/member.php?id=83997789"], "comments": "Kana prefix: マス"}, {"aliases": ["まにまに物販"], "pen_names": ["manika"], "position": "D02", "links": ["http://x.com/ma_ni_ka_"], "comments": "Kana prefix: マニ"}, {"aliases": ["マホウノシズク"], "pen_names": ["510、kana"], "position": "W01.02", "links": ["http://x.com/_magical_drop_", "http://www.nicovideo.jp/user/24202026"], "comments": "Kana prefix: マホ"}, {"aliases": ["真夜中おうどん倶楽部"], "pen_names": ["reinou/檀上大空"], "position": "A07.08", "links": ["http://x.com/skyw315", "http://www.nicovideo.jp/user/121319177"], "comments": "Kana prefix: マヨ"}, {"aliases": ["まるごとももかん"], "pen_names": ["雨音もも、あきかん さばこ"], "position": "F09.10", "links": ["http://x.com/Amane_moti"], "comments": "Kana prefix: マル"}, {"aliases": ["MIG"], "position": "C11", "links": ["http://x.com/moyashigroove"], "comments": "Kana prefix: ミグ"}, {"aliases": ["ミクバイクプロジェクト"], "pen_names": ["きつねづか"], "position": "E70", "links": ["http://x.com/cskitsunezuka", "http://www.nicovideo.jp/user/12339407"], "comments": "Kana prefix: ミク"}, {"aliases": ["みつあくま"], "pen_names": ["みつあくま"], "position": "C28", "links": ["https://www.youtube.com/channel/UCtne7wC5nEDx5p4JzJf9JHQ/", "http://x.com/mitsu_akuma"], "comments": "Kana prefix: ミツ"}, {"aliases": ["みっくすじゅーす"], "pen_names": ["るぅー、LonePi、ちかるとふ、rukaku、ココタロ"], "position": "B09.10", "links": ["https://twitter.com/MixedJuice_P", "http://x.com/CHIKARUTOF"], "comments": "Kana prefix: ミッ"}, {"aliases": ["みなみむきっちん"], "pen_names": ["榊みむ、南ノ南"], "position": "D51.52", "links": ["http://x.com/Kashiwa_mimu"], "comments": "Kana prefix: ミナ"}, {"aliases": ["みなる色の音紡ぎ"], "pen_names": ["みなるP"], "position": "B58", "links": ["https://minarup.tumblr.com/", "http://x.com/minarup", "http://www.nicovideo.jp/user/3864182"], "comments": "Kana prefix: ミナ"}, {"aliases": ["みょむ"], "pen_names": ["メロリカ、桜ようこ、おけい、むみそ"], "position": "C49.50", "links": ["http://x.com/melodic_hard"], "comments": "Kana prefix: ミョ"}, {"aliases": ["みるくかふぇ"], "pen_names": ["みるくかふぇ"], "position": "D69", "links": ["https://www.nicovideo.jp/mylist/45347852", "http://x.com/hiroys_milkcafe", "http://www.nicovideo.jp/user/29413826"], "comments": "Kana prefix: ミル"}, {"aliases": ["むげんるーぷ。"], "pen_names": ["しゅや"], "position": "F17", "links": ["http://x.com/syuyak61"], "comments": "Kana prefix: ムゲ"}, {"aliases": ["ムシぴのおうち"], "pen_names": ["ムシぴ"], "position": "B52", "links": ["http://muship.wixsite.com/muship", "http://x.com/muship_64", "http://www.nicovideo.jp/user/14764738"], "comments": "Kana prefix: ムシ"}, {"aliases": ["無邪気の箱庭"], "pen_names": ["ムジャオ"], "position": "D13", "links": ["http://mujamiku.fanbox.cc/", "http://x.com/mujamiku", "http://www.nicovideo.jp/user/3962735"], "comments": "Kana prefix: ムジ"}, {"aliases": ["酩酊堂"], "pen_names": ["ヒルヒ、のみか、巫泥、エレキモグラ"], "position": "B17.18", "links": ["https://www.youtube.com/c/MEITEIDO", "http://x.com/mememeMEITEIDO"], "comments": "Kana prefix: メイ"}, {"aliases": ["メキメキ寺temple"], "pen_names": ["メキメキ地蔵"], "position": "D24", "links": ["http://x.com/jizou_yeah"], "comments": "Kana prefix: メキ"}, {"aliases": ["Melville Records"], "pen_names": ["エイハブ"], "position": "B15.16", "links": ["http://x.com/AHUB_", "http://www.nicovideo.jp/user/95812305"], "comments": "Kana prefix: メル"}, {"aliases": ["メロンブックス"], "position": "企02", "links": ["https://www.melonbooks.co.jp/", "http://x.com/strongestmelon"], "comments": "Kana prefix: メロ"}, {"aliases": ["水雲のおみせ"], "position": "E29", "links": ["https://potofu.me/mozuku", "http://x.com/modumodumoduku"], "comments": "Kana prefix: モズ"}, {"aliases": ["もっちりうどん"], "pen_names": ["うどすけ"], "position": "E64", "links": ["http://x.com/kgami114_"], "comments": "Kana prefix: モッ"}, {"aliases": ["もとお工房"], "pen_names": ["もとお父"], "position": "F20", "links": ["https://motoopapa.booth.pm/", "http://x.com/motoo_papa", "http://www.nicovideo.jp/user/36075552"], "comments": "Kana prefix: モト"}, {"aliases": ["monaca:factory"], "pen_names": ["monaca:factory(10日P)"], "position": "A23", "links": ["https://www.nicovideo.jp/mylist/7105341", "http://x.com/monaca10p", "http://www.pixiv.net/member.php?id=1181093"], "comments": "Kana prefix: モナ"}, {"aliases": ["ヤギシロ"], "pen_names": ["ヤギシロ"], "position": "D10", "links": ["http://x.com/__yagishiro__"], "comments": "Kana prefix: ヤギ"}, {"aliases": ["焼肉塩キャベツ"], "pen_names": ["光彩よぞら、みうひぴ"], "position": "C56", "links": ["http://x.com/Hikari_yozora16"], "comments": "Kana prefix: ヤキ"}, {"aliases": ["ヤヤチョモランマ"], "pen_names": ["甘盛かふぇいん"], "position": "F29", "links": ["https://momyoraratityantan.tumblr.com/", "http://x.com/momyoraratityan", "http://www.pixiv.net/member.php?id=40363318"], "comments": "Kana prefix: ヤヤ"}, {"aliases": ["やわらかノート"], "pen_names": ["れれそふと"], "position": "F55", "links": ["http://x.com/rere_soft", "http://www.pixiv.net/member.php?id=7240443"], "comments": "Kana prefix: ヤワ"}, {"aliases": ["ゆいいつむに。"], "pen_names": ["えね"], "position": "E50", "links": ["http://x.com/ene105", "http://www.nicovideo.jp/user/38927934"], "comments": "Kana prefix: ユイ"}, {"aliases": ["夕季ハルノ"], "pen_names": ["夕季ハルノ"], "position": "E03.04", "links": ["http://x.com/yuhki_haruno"], "comments": "Kana prefix: ユウ"}, {"aliases": ["ゆうぐれさんぽ"], "pen_names": ["miri_1m"], "position": "E41", "links": ["http://x.com/miri_kyek", "http://www.pixiv.net/member.php?id=282454"], "comments": "Kana prefix: ユウ"}, {"aliases": ["UtopiaLyric × P∴Rhythmatiq"], "pen_names": ["UtopiaLyric、Aether_Eru、Noah"], "position": "E24", "links": ["https://utopialyric.xyz/", "http://x.com/yu_lyric", "http://www.pixiv.net/member.php?id=85663191"], "comments": "Kana prefix: ユウ"}, {"aliases": ["夕日工房"], "pen_names": ["戸津れんず"], "position": "D43", "links": ["http://x.com/E_MA_3", "http://www.pixiv.net/member.php?id=10008420"], "comments": "Kana prefix: ユウ"}, {"aliases": ["ユゥレイの怪奇譚"], "pen_names": ["ユゥレイの怪奇譚"], "position": "C30", "links": ["http://x.com/ULEInoKAIKITAN", "http://www.nicovideo.jp/user/48951879"], "comments": "Kana prefix: ユゥ"}, {"aliases": ["雪紅葉"], "pen_names": ["狸狐"], "position": "F13.14", "links": ["http://x.com/kaguya_riko_", "http://www.pixiv.net/member.php?id=2737491"], "comments": "Kana prefix: ユキ"}, {"aliases": ["U2tyaya。"], "pen_names": ["ゆずあじ。"], "position": "F56", "links": ["http://x.com/_yuzu_Taste", "http://www.pixiv.net/member.php?id=3284728"], "comments": "Kana prefix: ユズ"}, {"aliases": ["ゆずはちみつわさび"], "pen_names": ["柚葉わさ"], "position": "F44", "links": ["http://x.com/yuzuha_wasa", "http://www.pixiv.net/member.php?id=17671200"], "comments": "Kana prefix: ユズ"}, {"aliases": ["ゆゆこす"], "pen_names": ["ゆゆ"], "position": "E74", "links": ["http://x.com/Yuyuxcos"], "comments": "Kana prefix: ユユ"}, {"aliases": ["ゆるふわ すずゅしょっぷ"], "pen_names": ["ふゅゅ、szri"], "position": "E21", "links": ["http://x.com/Fuyusic"], "comments": "Kana prefix: ユル"}, {"aliases": ["横丁商店街"], "pen_names": ["浅葱紅音"], "position": "E65", "links": ["http://x.com/Arikaze_cos", "http://www.pixiv.net/member.php?id=7095244"], "comments": "Kana prefix: ヨコ"}, {"aliases": ["Y_Project"], "pen_names": ["弱音P"], "position": "B48", "links": ["http://x.com/yowanep", "http://www.pixiv.net/member.php?id=542851"], "comments": "Kana prefix: ヨワ"}, {"aliases": ["来世はねこになりたい"], "pen_names": ["あきた"], "position": "F11.12", "links": ["http://x.com/Akita_aaa2"], "comments": "Kana prefix: ライ"}, {"aliases": ["RASPBERRY POD"], "pen_names": ["noncom"], "position": "F53", "links": ["https://raspberrypod.hp.peraichi.com/", "http://x.com/noncomcom", "http://www.pixiv.net/member.php?id=559682"], "comments": "Kana prefix: ラズ"}, {"aliases": ["Re:ally"], "pen_names": ["信濃ナナ"], "position": "C33.34", "links": ["http://x.com/shinano_nana"], "comments": "Kana prefix: リア"}, {"aliases": ["Lizard House Orchestra"], "pen_names": ["ヒオ、嫌い、レン"], "position": "C48", "links": ["http://x.com/ren_nkjm", "http://www.nicovideo.jp/user/75183457"], "comments": "Kana prefix: リザ"}, {"aliases": ["リト"], "pen_names": ["リト"], "position": "C57", "links": ["https://t.co/C779MKUScr", "http://x.com/RiTo_8639"], "comments": "Kana prefix: リト"}, {"aliases": ["リフレイン"], "pen_names": ["みなづきじゅん"], "position": "F15", "comments": "Kana prefix: リフ"}, {"aliases": ["ryuryu / Past Days Sparkle"], "pen_names": ["ryuryu"], "position": "B57", "links": ["https://ryuryu-abhou.tumblr.com", "http://x.com/ryuryuephemera"], "comments": "Kana prefix: リュ"}, {"aliases": ["LiLRAIN"], "pen_names": ["美津紀、唯人、とも"], "position": "D60", "links": ["http://x.com/LiLRAIN81"], "comments": "Kana prefix: リル"}, {"aliases": ["Link Records"], "pen_names": ["浅上トモキ"], "position": "E02", "links": ["http://x.com/tomoki_123", "http://www.nicovideo.jp/user/513316"], "comments": "Kana prefix: リン"}, {"aliases": ["LUCY LOVE records"], "pen_names": ["おかいものPP"], "position": "C41", "links": ["https://lucylove.amebaownd.com", "http://x.com/okaimono_pp"], "comments": "Kana prefix: ルー"}, {"aliases": ["ROUTE23"], "pen_names": ["田淵フミ、*yuuka"], "position": "E34", "links": ["http://x.com/69thecasbah"], "comments": "Kana prefix: ルー"}, {"aliases": ["RuLu×Sumia×REISAI"], "pen_names": ["RuLu、Sumia、REISAI"], "position": "W17.18", "links": ["http://x.com/Su_mia_"], "comments": "Kana prefix: ルル"}, {"aliases": ["lain is not Rain"], "pen_names": ["lain"], "position": "C59", "links": ["https://www.nicovideo.jp/series/185325", "http://x.com/lainisnotrain", "http://www.nicovideo.jp/user/116829320"], "comments": "Kana prefix: レイ"}, {"aliases": ["REONAlD"], "pen_names": ["のぼる↑"], "position": "A26", "links": ["https://www.reonald.com/", "http://x.com/noboru_e", "http://www.nicovideo.jp/user/1136553"], "comments": "Kana prefix: レオ"}, {"aliases": ["Retriever Records"], "pen_names": ["buzzG"], "position": "A28", "links": ["http://buzzg.net/", "http://x.com/buzz_g", "http://www.pixiv.net/member.php?id=1286232"], "comments": "Kana prefix: レト"}, {"aliases": ["ローカ工房"], "pen_names": ["ローカスト"], "position": "C08", "links": ["https://www.youtube.com/channel/UCPFNdPkjzfgeTaZq54cH11g", "http://x.com/Locust223"], "comments": "Kana prefix: ロー"}, {"aliases": ["6月の絶界"], "pen_names": ["絶海、水無月"], "position": "C27", "links": ["https://zekkaihp.web.app/", "http://x.com/Zekkai_", "http://www.nicovideo.jp/user/17747959"], "comments": "Kana prefix: ロク"}, {"aliases": ["6種のごまだれ"], "pen_names": ["さくらゆな*"], "position": "F01", "links": ["https://gomadare-6.booth.pm/", "http://x.com/yuna_YJK", "http://www.pixiv.net/member.php?id=4255787"], "comments": "Kana prefix: ロク"}, {"aliases": ["Y-net"], "pen_names": ["芳田"], "position": "D05", "links": ["https://yoshidaynet.wixsite.com/y-net", "http://x.com/yoshida_yr"], "comments": "Kana prefix: ワイ"}, {"aliases": ["WILD COLOR RECORDS"], "pen_names": ["ヘルP"], "position": "D57.58", "links": ["https://www.nicovideo.jp/mylist/22039871", "http://x.com/sukenoji1", "http://www.nicovideo.jp/user/2066634"], "comments": "Kana prefix: ワイ"}, {"aliases": ["和ウナ制作委員会"], "pen_names": ["霧音 香 & 時流 絆 & しげむ"], "position": "D47", "links": ["http://wafuotomachi.wixsite.com/website", "http://x.com/kaori_kiRIne"], "comments": "Kana prefix: ワウ"}], "sources": [{"source": "Date, Participating circles: https://ketto.xsrv.jp/html/mimiken/clist.cgi?tvm49", "type": ["Reliable", "Official"]}], "media": [{"path": "49_20220802103817_tvm49CM.jpg", "sources": [{"source": "https://web.archive.org/web/20220802103817/https://ketto.com/tvm/tvm49CM.jpg", "type": ["Reliable", "Official"]}]}], "locations": [{"iframe_url": "https://www.google.com/maps/embed?pb=!1m18!1m12!1m3!1d1622.4614245873063!2d139.74702373866853!3d35.58029602459979!2m3!1f0!2f0!3f0!3m2!1i1024!2i768!4f13.1!3m3!1m2!1s0x601861bc691ff473%3A0x3c65b91947c29bba!2sTRC%20First%20Exhibition%20Hall!5e0!3m2!1sen!2sfr!4v1766790392057!5m2!1sen!2sfr", "description": "TRC東京流通センター第一展示場ABホール ", "sources": [{"source": "https://ketto.xsrv.jp/html/mimiken/clist.cgi?tvm49", "type": ["Reliable", "Official"]}]}]}